{
    "sourceFile": "src/views/Search.js",
    "activeCommit": 0,
    "commits": [
        {
            "activePatchIndex": 3,
            "patches": [
                {
                    "date": 1715833143235,
                    "content": "Index: \n===================================================================\n--- \n+++ \n"
                },
                {
                    "date": 1716193032325,
                    "content": "Index: \n===================================================================\n--- \n+++ \n@@ -6,9 +6,12 @@\n import SearchList from \"../components/main/SearchList\"; \n import localmap_img from \"../assets/images/bg/localmap_img.png\";\n import mymap_img from \"../assets/images/bg/mymap_img.png\";\n import HistoryPost from \"../components/main/HistoryPost\";\n+import FollowingList from './FollowingsList';\n \n+\n+\n const Search = () => {\n   const [rpost, setRPost] = useState([]);\n   const [selectedPost, setSelectedPost] = useState(null); // 선택된 게시글 상태\n   const [filterToggle, setFilterToggle] = useState(false); // 토글 상태\n@@ -80,9 +83,9 @@\n       )}\n \n       {/* 로컬맵, 마이맵 이동 버튼 */}\n       <div className=\"group98-group77\">\n-        {/* 로컬맵 이동 */}\n+        로컬맵 이동\n         <Link to=\"/localmap\" style={{ textDecoration: \"none\", color: \"inherit\" }}>\n           <button style={{ border: \"none\" }}>\n             <img\n               src={localmap_img}\n@@ -107,9 +110,11 @@\n               마이맵으로 이동하기\n             </span>\n           </button>\n         </Link>\n+        <FollowingList />\n       </div>\n+     \n     </div>\n   );\n };\n \n"
                },
                {
                    "date": 1716193042781,
                    "content": "Index: \n===================================================================\n--- \n+++ \n@@ -6,9 +6,12 @@\n import SearchList from \"../components/main/SearchList\"; \n import localmap_img from \"../assets/images/bg/localmap_img.png\";\n import mymap_img from \"../assets/images/bg/mymap_img.png\";\n import HistoryPost from \"../components/main/HistoryPost\";\n+import FollowingList from './FollowingsList';\n \n+\n+\n const Search = () => {\n   const [rpost, setRPost] = useState([]);\n   const [selectedPost, setSelectedPost] = useState(null); // 선택된 게시글 상태\n   const [filterToggle, setFilterToggle] = useState(false); // 토글 상태\n@@ -80,9 +83,9 @@\n       )}\n \n       {/* 로컬맵, 마이맵 이동 버튼 */}\n       <div className=\"group98-group77\">\n-        {/* 로컬맵 이동 */}\n+        로컬맵 이동\n         <Link to=\"/localmap\" style={{ textDecoration: \"none\", color: \"inherit\" }}>\n           <button style={{ border: \"none\" }}>\n             <img\n               src={localmap_img}\n@@ -107,9 +110,11 @@\n               마이맵으로 이동하기\n             </span>\n           </button>\n         </Link>\n+        <FollowingList />\n       </div>\n+     \n     </div>\n   );\n };\n \n"
                },
                {
                    "date": 1716193227429,
                    "content": "Index: \n===================================================================\n--- \n+++ \n@@ -0,0 +1,117 @@\n+import React, { useState, useEffect } from 'react';\n+import { Link } from 'react-router-dom';\n+import \"../assets/scss/layout/_search.scss\";\n+import magnifier from \"../assets/images/logos/magnifier.png\";\n+import arrow from \"../assets/images/logos/arrow.png\";\n+import SearchList from \"../components/main/SearchList\"; \n+import localmap_img from \"../assets/images/bg/localmap_img.png\";\n+import mymap_img from \"../assets/images/bg/mymap_img.png\";\n+import HistoryPost from \"../components/main/HistoryPost\";\n+\n+const Search = () => {\n+  const [rpost, setRPost] = useState([]);\n+  const [selectedPost, setSelectedPost] = useState(null); // 선택된 게시글 상태\n+  const [filterToggle, setFilterToggle] = useState(false); // 토글 상태\n+\n+  useEffect(() => {\n+    fetch('http://localhost:3001/recomendPost') //API경로 적어주기\n+      .then(res => res.json())\n+      .then(data => setRPost(data))\n+      .catch(error => console.error(\"Error fetching data:\", error));\n+  }, []);\n+\n+  const handlePostClick = (selectedItem) => {\n+    setSelectedPost(selectedItem);\n+  };\n+\n+  const handleBackClick = () => {\n+    setSelectedPost(null); // 선택된 포스트 초기화\n+  };\n+\n+  const toggleFilter = () => {\n+    setFilterToggle(!filterToggle);\n+  };\n+\n+  return (\n+    <div className=\"group98-group98\">\n+      <div className=\"group98-frame\">\n+        {/* 검색창 */}\n+        <div className=\"group98-frame\">\n+          {/* 검색창 내용 */}\n+        </div>\n+        {/* 토글 버튼 */}\n+        <div className=\"group98-frame2\" onClick={toggleFilter}>\n+          <div className=\"group98-svg\" />\n+          <button style={{ border: \"none\" }}>\n+            <img\n+              src={arrow}\n+              alt=\"토글 화살표\"\n+              className=\"group98-svg01\"\n+            />\n+          </button>\n+          <span className=\"group98-text02\">\n+            <span>필터</span>\n+          </span>\n+          {/* 토글된 상태일 때, 필터 목록 표시 */}\n+          {filterToggle && (\n+            <div className=\"filter-buttons\">\n+              <button className=\"filter-button\">닉네임</button>\n+              <button className=\"filter-button\">해시태그</button>\n+              <button className=\"filter-button\">제목+내용</button>\n+            </div>\n+          )}\n+        </div>\n+      </div>\n+\n+      {/* 추천 게시글 목록 */}\n+      <div className=\"group98-frame-profile\">\n+        {rpost.map(item => (\n+          <button style={{ border: \"none\" }} key={item.id} onClick={() => handlePostClick(item)}>\n+            <SearchList data={item} />\n+          </button>\n+        ))}\n+      </div>\n+\n+      {/* 선택된 포스트 표시 */}\n+      {selectedPost && (\n+        <div className=\"historyPost-con\">\n+          <HistoryPost data={selectedPost} onClose={handleBackClick} />\n+        </div>\n+      )}\n+\n+      {/* 로컬맵, 마이맵 이동 버튼 */}\n+      <div className=\"group98-group77\">\n+        로컬맵 이동\n+        <Link to=\"/localmap\" style={{ textDecoration: \"none\", color: \"inherit\" }}>\n+          <button style={{ border: \"none\" }}>\n+            <img\n+              src={localmap_img}\n+              alt=\"localmap\"\n+              className=\"group98-localmap\"\n+            />\n+            <span className=\"group98-text46\">\n+              로컬맵으로 돌아가기\n+            </span>\n+          </button>\n+        </Link>\n+\n+        {/* 마이맵 이동 */}\n+        <Link to=\"/mymap\" style={{ textDecoration: \"none\", color: \"inherit\" }}>\n+          <button style={{ border: \"none\" }}>\n+            <img\n+              src={mymap_img}\n+              alt=\"mymap\"\n+              className=\"group98-mymap\"\n+            />\n+            <span className=\"group98-text49\">\n+              마이맵으로 이동하기\n+            </span>\n+          </button>\n+        </Link>\n+      </div>\n+     \n+    </div>\n+  );\n+};\n+\n+export default Search;\n"
                }
            ],
            "date": 1715833143235,
            "name": "Commit-0",
            "content": "import React, { useState, useEffect } from 'react';\nimport { Link } from 'react-router-dom';\nimport \"../assets/scss/layout/_search.scss\";\nimport magnifier from \"../assets/images/logos/magnifier.png\";\nimport arrow from \"../assets/images/logos/arrow.png\";\nimport SearchList from \"../components/main/SearchList\"; \nimport localmap_img from \"../assets/images/bg/localmap_img.png\";\nimport mymap_img from \"../assets/images/bg/mymap_img.png\";\nimport HistoryPost from \"../components/main/HistoryPost\";\n\nconst Search = () => {\n  const [rpost, setRPost] = useState([]);\n  const [selectedPost, setSelectedPost] = useState(null); // 선택된 게시글 상태\n  const [filterToggle, setFilterToggle] = useState(false); // 토글 상태\n\n  useEffect(() => {\n    fetch('http://localhost:3001/recomendPost') //API경로 적어주기\n      .then(res => res.json())\n      .then(data => setRPost(data))\n      .catch(error => console.error(\"Error fetching data:\", error));\n  }, []);\n\n  const handlePostClick = (selectedItem) => {\n    setSelectedPost(selectedItem);\n  };\n\n  const handleBackClick = () => {\n    setSelectedPost(null); // 선택된 포스트 초기화\n  };\n\n  const toggleFilter = () => {\n    setFilterToggle(!filterToggle);\n  };\n\n  return (\n    <div className=\"group98-group98\">\n      <div className=\"group98-frame\">\n        {/* 검색창 */}\n        <div className=\"group98-frame\">\n          {/* 검색창 내용 */}\n        </div>\n        {/* 토글 버튼 */}\n        <div className=\"group98-frame2\" onClick={toggleFilter}>\n          <div className=\"group98-svg\" />\n          <button style={{ border: \"none\" }}>\n            <img\n              src={arrow}\n              alt=\"토글 화살표\"\n              className=\"group98-svg01\"\n            />\n          </button>\n          <span className=\"group98-text02\">\n            <span>필터</span>\n          </span>\n          {/* 토글된 상태일 때, 필터 목록 표시 */}\n          {filterToggle && (\n            <div className=\"filter-buttons\">\n              <button className=\"filter-button\">닉네임</button>\n              <button className=\"filter-button\">해시태그</button>\n              <button className=\"filter-button\">제목+내용</button>\n            </div>\n          )}\n        </div>\n      </div>\n\n      {/* 추천 게시글 목록 */}\n      <div className=\"group98-frame-profile\">\n        {rpost.map(item => (\n          <button style={{ border: \"none\" }} key={item.id} onClick={() => handlePostClick(item)}>\n            <SearchList data={item} />\n          </button>\n        ))}\n      </div>\n\n      {/* 선택된 포스트 표시 */}\n      {selectedPost && (\n        <div className=\"historyPost-con\">\n          <HistoryPost data={selectedPost} onClose={handleBackClick} />\n        </div>\n      )}\n\n      {/* 로컬맵, 마이맵 이동 버튼 */}\n      <div className=\"group98-group77\">\n        {/* 로컬맵 이동 */}\n        <Link to=\"/localmap\" style={{ textDecoration: \"none\", color: \"inherit\" }}>\n          <button style={{ border: \"none\" }}>\n            <img\n              src={localmap_img}\n              alt=\"localmap\"\n              className=\"group98-localmap\"\n            />\n            <span className=\"group98-text46\">\n              로컬맵으로 돌아가기\n            </span>\n          </button>\n        </Link>\n\n        {/* 마이맵 이동 */}\n        <Link to=\"/mymap\" style={{ textDecoration: \"none\", color: \"inherit\" }}>\n          <button style={{ border: \"none\" }}>\n            <img\n              src={mymap_img}\n              alt=\"mymap\"\n              className=\"group98-mymap\"\n            />\n            <span className=\"group98-text49\">\n              마이맵으로 이동하기\n            </span>\n          </button>\n        </Link>\n      </div>\n    </div>\n  );\n};\n\nexport default Search;\n"
        }
    ]
}